git_dates_modifier/__init__.py
git_dates_modifier/main.py
git_dates_modifier-0.1.0.dist-info/licenses/LICENSE
git_dates_modifier-0.1.0.dist-info/METADATA
git_dates_modifier-0.1.0.dist-info/WHEEL
git_dates_modifier-0.1.0.dist-info/entry_points.txt
git_dates_modifier-0.1.0.dist-info/top_level.txt
git_dates_modifier-0.1.0.dist-info/RECORD
