Metadata-Version: 2.4
Name: git-dates-modifier
Version: 0.1.0
Summary: Interactively rewrite Git commit author and committer dates.
Author: xissium
License: The MIT License (MIT)
Project-URL: Homepage, https://github.com/xissium/git-dates-modifier
Project-URL: Repository, https://github.com/xissium/git-dates-modifier
Keywords: git,history,commit,date,git-filter-repo
Classifier: Programming Language :: Python :: 3
Requires-Python: >=3.8
License-File: LICENSE
Requires-Dist: git-filter-repo
Dynamic: license-file
